wast/__init__.py
wast/common.py
wast/fragments.py
wast/helpers.py
wast/nodes.py
wast/utils.py
wast/validators.py
wast-0.0.3.dist-info/METADATA
wast-0.0.3.dist-info/WHEEL
wast-0.0.3.dist-info/top_level.txt
wast-0.0.3.dist-info/RECORD
